{
    "relationships": [],
    "fields": [
        {
            "fieldId": 1,
            "fieldName": "name",
            "fieldType": "String"
        },
        {
            "fieldId": 2,
            "fieldName": "mass",
            "fieldType": "Float",
            "fieldValidateRules": [
                "min"
            ],
            "fieldValidateRulesMin": "0"
        }
    ],
    "changelogDate": "20160125205657",
    "dto": "mapstruct",
    "service": "serviceImpl",
    "pagination": "no"
}